<?xml version="1.0" encoding="UTF-8"?>
<TestPlanItem index="0">
  <GazeDataProviderType>Dummy</GazeDataProviderType>
  <BasicGazeTarget>
    <FeedbackCursor>1</FeedbackCursor>
    <NumberOfButtons>2</NumberOfButtons>
    <ButtonHeightRatio>118</ButtonHeightRatio>
    <DeadSpace>100</DeadSpace>
    <SelectionTriggerType>KeyboardKeyC</SelectionTriggerType>
  </BasicGazeTarget>
  <RepetitionType>RANDOM_NO_SUCCESSIVE_REPEATS</RepetitionType>
  <NumberOfSelections>1</NumberOfSelections>
  <ResultTarget index="0">
    <IntendedTargetItemIndex>0</IntendedTargetItemIndex>
    <SelectedTargetItemIndex>0</SelectedTargetItemIndex>
    <TimeNeeded>875</TimeNeeded>
    <TimeTickStart>1125483194706322</TimeTickStart>
    <TimeTickTriggered>1125484069194307</TimeTickTriggered>
    <RawGazePoints>
      <GazePoint>
        <X>528</X>
        <Y>196</Y>
        <TimeTick>1125484056092995</TimeTick>
        <Validity>VALID</Validity>
      </GazePoint>
      <GazePoint>
        <X>528</X>
        <Y>196</Y>
        <TimeTick>1125484040083942</TimeTick>
        <Validity>VALID</Validity>
      </GazePoint>
      <GazePoint>
        <X>528</X>
        <Y>196</Y>
        <TimeTick>1125484024070567</TimeTick>
        <Validity>VALID</Validity>
      </GazePoint>
      <GazePoint>
        <X>528</X>
        <Y>196</Y>
        <TimeTick>1125484008080420</TimeTick>
        <Validity>VALID</Validity>
      </GazePoint>
      <GazePoint>
        <X>528</X>
        <Y>196</Y>
        <TimeTick>1125483992017890</TimeTick>
        <Validity>VALID</Validity>
      </GazePoint>
      <GazePoint>
        <X>528</X>
        <Y>196</Y>
        <TimeTick>1125483976030444</TimeTick>
        <Validity>VALID</Validity>
      </GazePoint>
      <GazePoint>
        <X>528</X>
        <Y>196</Y>
        <TimeTick>1125483960037055</TimeTick>
        <Validity>VALID</Validity>
      </GazePoint>
      <GazePoint>
        <X>528</X>
        <Y>196</Y>
        <TimeTick>1125483944018819</TimeTick>
        <Validity>VALID</Validity>
      </GazePoint>
      <GazePoint>
        <X>528</X>
        <Y>196</Y>
        <TimeTick>1125483928007065</TimeTick>
        <Validity>VALID</Validity>
      </GazePoint>
      <GazePoint>
        <X>528</X>
        <Y>196</Y>
        <TimeTick>1125483911957499</TimeTick>
        <Validity>VALID</Validity>
      </GazePoint>
      <GazePoint>
        <X>528</X>
        <Y>196</Y>
        <TimeTick>1125483895997601</TimeTick>
        <Validity>VALID</Validity>
      </GazePoint>
      <GazePoint>
        <X>528</X>
        <Y>196</Y>
        <TimeTick>1125483879949115</TimeTick>
        <Validity>VALID</Validity>
      </GazePoint>
      <GazePoint>
        <X>528</X>
        <Y>196</Y>
        <TimeTick>1125483863924397</TimeTick>
        <Validity>VALID</Validity>
      </GazePoint>
      <GazePoint>
        <X>532</X>
        <Y>199</Y>
        <TimeTick>1125483847953696</TimeTick>
        <Validity>VALID</Validity>
      </GazePoint>
      <GazePoint>
        <X>532</X>
        <Y>198</Y>
        <TimeTick>1125483831914393</TimeTick>
        <Validity>VALID</Validity>
      </GazePoint>
      <GazePoint>
        <X>531</X>
        <Y>198</Y>
        <TimeTick>1125483816289402</TimeTick>
        <Validity>VALID</Validity>
      </GazePoint>
      <GazePoint>
        <X>531</X>
        <Y>198</Y>
        <TimeTick>1125483799945442</TimeTick>
        <Validity>VALID</Validity>
      </GazePoint>
      <GazePoint>
        <X>531</X>
        <Y>198</Y>
        <TimeTick>1125483783905059</TimeTick>
        <Validity>VALID</Validity>
      </GazePoint>
      <GazePoint>
        <X>531</X>
        <Y>198</Y>
        <TimeTick>1125483767866837</TimeTick>
        <Validity>VALID</Validity>
      </GazePoint>
      <GazePoint>
        <X>531</X>
        <Y>198</Y>
        <TimeTick>1125483751905859</TimeTick>
        <Validity>VALID</Validity>
      </GazePoint>
      <GazePoint>
        <X>531</X>
        <Y>198</Y>
        <TimeTick>1125483735884381</TimeTick>
        <Validity>VALID</Validity>
      </GazePoint>
      <GazePoint>
        <X>531</X>
        <Y>198</Y>
        <TimeTick>1125483719849400</TimeTick>
        <Validity>VALID</Validity>
      </GazePoint>
      <GazePoint>
        <X>530</X>
        <Y>197</Y>
        <TimeTick>1125483703826842</TimeTick>
        <Validity>VALID</Validity>
      </GazePoint>
      <GazePoint>
        <X>530</X>
        <Y>197</Y>
        <TimeTick>1125483688244524</TimeTick>
        <Validity>VALID</Validity>
      </GazePoint>
      <GazePoint>
        <X>528</X>
        <Y>196</Y>
        <TimeTick>1125483671831423</TimeTick>
        <Validity>VALID</Validity>
      </GazePoint>
      <GazePoint>
        <X>528</X>
        <Y>196</Y>
        <TimeTick>1125483655833713</TimeTick>
        <Validity>VALID</Validity>
      </GazePoint>
      <GazePoint>
        <X>528</X>
        <Y>196</Y>
        <TimeTick>1125483639846807</TimeTick>
        <Validity>VALID</Validity>
      </GazePoint>
      <GazePoint>
        <X>528</X>
        <Y>196</Y>
        <TimeTick>1125483623825870</TimeTick>
        <Validity>VALID</Validity>
      </GazePoint>
      <GazePoint>
        <X>528</X>
        <Y>196</Y>
        <TimeTick>1125483607811955</TimeTick>
        <Validity>VALID</Validity>
      </GazePoint>
      <GazePoint>
        <X>528</X>
        <Y>196</Y>
        <TimeTick>1125483591542539</TimeTick>
        <Validity>VALID</Validity>
      </GazePoint>
      <GazePoint>
        <X>528</X>
        <Y>196</Y>
        <TimeTick>1125483574793451</TimeTick>
        <Validity>VALID</Validity>
      </GazePoint>
      <GazePoint>
        <X>528</X>
        <Y>196</Y>
        <TimeTick>1125483558772515</TimeTick>
        <Validity>VALID</Validity>
      </GazePoint>
      <GazePoint>
        <X>528</X>
        <Y>196</Y>
        <TimeTick>1125483542775885</TimeTick>
        <Validity>VALID</Validity>
      </GazePoint>
      <GazePoint>
        <X>528</X>
        <Y>196</Y>
        <TimeTick>1125483526776555</TimeTick>
        <Validity>VALID</Validity>
      </GazePoint>
      <GazePoint>
        <X>528</X>
        <Y>196</Y>
        <TimeTick>1125483510738333</TimeTick>
        <Validity>VALID</Validity>
      </GazePoint>
      <GazePoint>
        <X>528</X>
        <Y>196</Y>
        <TimeTick>1125483494694168</TimeTick>
        <Validity>VALID</Validity>
      </GazePoint>
      <GazePoint>
        <X>528</X>
        <Y>196</Y>
        <TimeTick>1125483478688356</TimeTick>
        <Validity>VALID</Validity>
      </GazePoint>
      <GazePoint>
        <X>528</X>
        <Y>196</Y>
        <TimeTick>1125483462755467</TimeTick>
        <Validity>VALID</Validity>
      </GazePoint>
      <GazePoint>
        <X>528</X>
        <Y>196</Y>
        <TimeTick>1125483446691856</TimeTick>
        <Validity>VALID</Validity>
      </GazePoint>
      <GazePoint>
        <X>528</X>
        <Y>196</Y>
        <TimeTick>1125483430686584</TimeTick>
        <Validity>VALID</Validity>
      </GazePoint>
      <GazePoint>
        <X>528</X>
        <Y>196</Y>
        <TimeTick>1125483414717504</TimeTick>
        <Validity>VALID</Validity>
      </GazePoint>
      <GazePoint>
        <X>528</X>
        <Y>196</Y>
        <TimeTick>1125483398638768</TimeTick>
        <Validity>VALID</Validity>
      </GazePoint>
      <GazePoint>
        <X>528</X>
        <Y>203</Y>
        <TimeTick>1125483382597845</TimeTick>
        <Validity>VALID</Validity>
      </GazePoint>
      <GazePoint>
        <X>528</X>
        <Y>206</Y>
        <TimeTick>1125483366602836</TimeTick>
        <Validity>VALID</Validity>
      </GazePoint>
      <GazePoint>
        <X>528</X>
        <Y>207</Y>
        <TimeTick>1125483350722343</TimeTick>
        <Validity>VALID</Validity>
      </GazePoint>
      <GazePoint>
        <X>528</X>
        <Y>207</Y>
        <TimeTick>1125483334570145</TimeTick>
        <Validity>VALID</Validity>
      </GazePoint>
      <GazePoint>
        <X>529</X>
        <Y>207</Y>
        <TimeTick>1125483318583779</TimeTick>
        <Validity>VALID</Validity>
      </GazePoint>
      <GazePoint>
        <X>529</X>
        <Y>207</Y>
        <TimeTick>1125483302829686</TimeTick>
        <Validity>VALID</Validity>
      </GazePoint>
      <GazePoint>
        <X>532</X>
        <Y>205</Y>
        <TimeTick>1125483286594841</TimeTick>
        <Validity>VALID</Validity>
      </GazePoint>
      <GazePoint>
        <X>537</X>
        <Y>198</Y>
        <TimeTick>1125483270536633</TimeTick>
        <Validity>VALID</Validity>
      </GazePoint>
      <GazePoint>
        <X>539</X>
        <Y>195</Y>
        <TimeTick>1125483254836557</TimeTick>
        <Validity>VALID</Validity>
      </GazePoint>
      <GazePoint>
        <X>539</X>
        <Y>195</Y>
        <TimeTick>1125483238654649</TimeTick>
        <Validity>VALID</Validity>
      </GazePoint>
      <GazePoint>
        <X>539</X>
        <Y>195</Y>
        <TimeTick>1125483222737965</TimeTick>
        <Validity>VALID</Validity>
      </GazePoint>
      <GazePoint>
        <X>536</X>
        <Y>195</Y>
        <TimeTick>1125483206591708</TimeTick>
        <Validity>VALID</Validity>
      </GazePoint>
      <GazePoint>
        <X>523</X>
        <Y>196</Y>
        <TimeTick>1125483190491366</TimeTick>
        <Validity>VALID</Validity>
      </GazePoint>
    </RawGazePoints>
    <RawFutureGazePoints>
      <GazePoint>
        <X>528</X>
        <Y>196</Y>
        <TimeTick>1125484072093406</TimeTick>
        <Validity>PARTIALLY_VALID</Validity>
      </GazePoint>
      <GazePoint>
        <X>528</X>
        <Y>196</Y>
        <TimeTick>1125484088107321</TimeTick>
        <Validity>PARTIALLY_VALID</Validity>
      </GazePoint>
      <GazePoint>
        <X>528</X>
        <Y>196</Y>
        <TimeTick>1125484104130419</TimeTick>
        <Validity>PARTIALLY_VALID</Validity>
      </GazePoint>
      <GazePoint>
        <X>528</X>
        <Y>196</Y>
        <TimeTick>1125484120107061</TimeTick>
        <Validity>PARTIALLY_VALID</Validity>
      </GazePoint>
      <GazePoint>
        <X>528</X>
        <Y>196</Y>
        <TimeTick>1125484136112334</TimeTick>
        <Validity>PARTIALLY_VALID</Validity>
      </GazePoint>
      <GazePoint>
        <X>528</X>
        <Y>196</Y>
        <TimeTick>1125484152164601</TimeTick>
        <Validity>PARTIALLY_VALID</Validity>
      </GazePoint>
      <GazePoint>
        <X>528</X>
        <Y>196</Y>
        <TimeTick>1125484168165551</TimeTick>
        <Validity>PARTIALLY_VALID</Validity>
      </GazePoint>
      <GazePoint>
        <X>528</X>
        <Y>196</Y>
        <TimeTick>1125484184153538</TimeTick>
        <Validity>PARTIALLY_VALID</Validity>
      </GazePoint>
      <GazePoint>
        <X>528</X>
        <Y>196</Y>
        <TimeTick>1125484200162591</TimeTick>
        <Validity>VALID</Validity>
      </GazePoint>
      <GazePoint>
        <X>528</X>
        <Y>196</Y>
        <TimeTick>1125484216192711</TimeTick>
        <Validity>VALID</Validity>
      </GazePoint>
      <GazePoint>
        <X>528</X>
        <Y>196</Y>
        <TimeTick>1125484232188800</TimeTick>
        <Validity>VALID</Validity>
      </GazePoint>
      <GazePoint>
        <X>528</X>
        <Y>196</Y>
        <TimeTick>1125484248206496</TimeTick>
        <Validity>VALID</Validity>
      </GazePoint>
      <GazePoint>
        <X>528</X>
        <Y>196</Y>
        <TimeTick>1125484264259843</TimeTick>
        <Validity>VALID</Validity>
      </GazePoint>
      <GazePoint>
        <X>528</X>
        <Y>196</Y>
        <TimeTick>1125484280208938</TimeTick>
        <Validity>VALID</Validity>
      </GazePoint>
      <GazePoint>
        <X>528</X>
        <Y>196</Y>
        <TimeTick>1125484296222853</TimeTick>
        <Validity>VALID</Validity>
      </GazePoint>
      <GazePoint>
        <X>528</X>
        <Y>196</Y>
        <TimeTick>1125484312234066</TimeTick>
        <Validity>VALID</Validity>
      </GazePoint>
      <GazePoint>
        <X>528</X>
        <Y>196</Y>
        <TimeTick>1125484328263646</TimeTick>
        <Validity>VALID</Validity>
      </GazePoint>
      <GazePoint>
        <X>528</X>
        <Y>196</Y>
        <TimeTick>1125484344263517</TimeTick>
        <Validity>VALID</Validity>
      </GazePoint>
      <GazePoint>
        <X>528</X>
        <Y>196</Y>
        <TimeTick>1125484360277972</TimeTick>
        <Validity>VALID</Validity>
      </GazePoint>
      <GazePoint>
        <X>528</X>
        <Y>196</Y>
        <TimeTick>1125484376289186</TimeTick>
        <Validity>VALID</Validity>
      </GazePoint>
    </RawFutureGazePoints>
  </ResultTarget>
</TestPlanItem>
