<?xml version="1.0" encoding="UTF-8"?>
<TestPlanItem index="0">
  <GazeDataProviderType>Dummy</GazeDataProviderType>
  <BasicGazeTarget>
    <FeedbackCursor>1</FeedbackCursor>
    <NumberOfButtons>2</NumberOfButtons>
    <ButtonHeightRatio>60</ButtonHeightRatio>
    <DeadSpace>60</DeadSpace>
    <SelectionTriggerType>KeyboardKeyC</SelectionTriggerType>
  </BasicGazeTarget>
  <RepetitionType>RANDOM_NO_SUCCESSIVE_REPEATS</RepetitionType>
  <NumberOfSelections>1</NumberOfSelections>
  <ResultTarget index="0">
    <IntendedTargetItemIndex>1</IntendedTargetItemIndex>
    <SelectedTargetItemIndex>1</SelectedTargetItemIndex>
    <TimeNeeded>2701</TimeNeeded>
    <TimeTickStart>438053102908607</TimeTickStart>
    <TimeTickTriggered>438055803024852</TimeTickTriggered>
    <RawGazePoints>
      <GazePoint>
        <X>502</X>
        <Y>304</Y>
        <TimeTick>438055804103574</TimeTick>
        <Validity>VALID</Validity>
      </GazePoint>
      <GazePoint>
        <X>502</X>
        <Y>304</Y>
        <TimeTick>438055787812003</TimeTick>
        <Validity>VALID</Validity>
      </GazePoint>
      <GazePoint>
        <X>502</X>
        <Y>304</Y>
        <TimeTick>438055771743522</TimeTick>
        <Validity>VALID</Validity>
      </GazePoint>
      <GazePoint>
        <X>502</X>
        <Y>304</Y>
        <TimeTick>438055755538378</TimeTick>
        <Validity>VALID</Validity>
      </GazePoint>
      <GazePoint>
        <X>502</X>
        <Y>304</Y>
        <TimeTick>438055739020474</TimeTick>
        <Validity>VALID</Validity>
      </GazePoint>
      <GazePoint>
        <X>502</X>
        <Y>304</Y>
        <TimeTick>438055723006551</TimeTick>
        <Validity>VALID</Validity>
      </GazePoint>
      <GazePoint>
        <X>502</X>
        <Y>304</Y>
        <TimeTick>438055706966699</TimeTick>
        <Validity>VALID</Validity>
      </GazePoint>
      <GazePoint>
        <X>502</X>
        <Y>304</Y>
        <TimeTick>438055690973842</TimeTick>
        <Validity>VALID</Validity>
      </GazePoint>
      <GazePoint>
        <X>502</X>
        <Y>304</Y>
        <TimeTick>438055675441212</TimeTick>
        <Validity>VALID</Validity>
      </GazePoint>
      <GazePoint>
        <X>502</X>
        <Y>304</Y>
        <TimeTick>438055658229188</TimeTick>
        <Validity>VALID</Validity>
      </GazePoint>
      <GazePoint>
        <X>502</X>
        <Y>304</Y>
        <TimeTick>438055641861992</TimeTick>
        <Validity>VALID</Validity>
      </GazePoint>
      <GazePoint>
        <X>502</X>
        <Y>304</Y>
        <TimeTick>438055625805935</TimeTick>
        <Validity>VALID</Validity>
      </GazePoint>
      <GazePoint>
        <X>502</X>
        <Y>304</Y>
        <TimeTick>438055608907211</TimeTick>
        <Validity>VALID</Validity>
      </GazePoint>
      <GazePoint>
        <X>502</X>
        <Y>304</Y>
        <TimeTick>438055591971215</TimeTick>
        <Validity>VALID</Validity>
      </GazePoint>
      <GazePoint>
        <X>502</X>
        <Y>304</Y>
        <TimeTick>438055575994023</TimeTick>
        <Validity>VALID</Validity>
      </GazePoint>
      <GazePoint>
        <X>502</X>
        <Y>304</Y>
        <TimeTick>438055558980782</TimeTick>
        <Validity>VALID</Validity>
      </GazePoint>
      <GazePoint>
        <X>502</X>
        <Y>304</Y>
        <TimeTick>438055542935529</TimeTick>
        <Validity>VALID</Validity>
      </GazePoint>
      <GazePoint>
        <X>502</X>
        <Y>304</Y>
        <TimeTick>438055527453674</TimeTick>
        <Validity>VALID</Validity>
      </GazePoint>
      <GazePoint>
        <X>502</X>
        <Y>304</Y>
        <TimeTick>438055508916610</TimeTick>
        <Validity>VALID</Validity>
      </GazePoint>
      <GazePoint>
        <X>502</X>
        <Y>304</Y>
        <TimeTick>438055492541312</TimeTick>
        <Validity>VALID</Validity>
      </GazePoint>
      <GazePoint>
        <X>502</X>
        <Y>304</Y>
        <TimeTick>438055476350212</TimeTick>
        <Validity>VALID</Validity>
      </GazePoint>
      <GazePoint>
        <X>502</X>
        <Y>304</Y>
        <TimeTick>438055459638387</TimeTick>
        <Validity>VALID</Validity>
      </GazePoint>
      <GazePoint>
        <X>502</X>
        <Y>304</Y>
        <TimeTick>438055443467274</TimeTick>
        <Validity>VALID</Validity>
      </GazePoint>
      <GazePoint>
        <X>502</X>
        <Y>304</Y>
        <TimeTick>438055427351258</TimeTick>
        <Validity>VALID</Validity>
      </GazePoint>
      <GazePoint>
        <X>502</X>
        <Y>304</Y>
        <TimeTick>438055411332473</TimeTick>
        <Validity>VALID</Validity>
      </GazePoint>
      <GazePoint>
        <X>502</X>
        <Y>304</Y>
        <TimeTick>438055395321250</TimeTick>
        <Validity>VALID</Validity>
      </GazePoint>
      <GazePoint>
        <X>502</X>
        <Y>304</Y>
        <TimeTick>438055379288421</TimeTick>
        <Validity>VALID</Validity>
      </GazePoint>
      <GazePoint>
        <X>502</X>
        <Y>304</Y>
        <TimeTick>438055363328515</TimeTick>
        <Validity>VALID</Validity>
      </GazePoint>
      <GazePoint>
        <X>502</X>
        <Y>304</Y>
        <TimeTick>438055347410201</TimeTick>
        <Validity>VALID</Validity>
      </GazePoint>
      <GazePoint>
        <X>502</X>
        <Y>304</Y>
        <TimeTick>438055331247191</TimeTick>
        <Validity>VALID</Validity>
      </GazePoint>
      <GazePoint>
        <X>502</X>
        <Y>304</Y>
        <TimeTick>438055315285664</TimeTick>
        <Validity>VALID</Validity>
      </GazePoint>
      <GazePoint>
        <X>502</X>
        <Y>304</Y>
        <TimeTick>438055299225286</TimeTick>
        <Validity>VALID</Validity>
      </GazePoint>
      <GazePoint>
        <X>502</X>
        <Y>304</Y>
        <TimeTick>438055283214063</TimeTick>
        <Validity>VALID</Validity>
      </GazePoint>
      <GazePoint>
        <X>502</X>
        <Y>304</Y>
        <TimeTick>438055267217965</TimeTick>
        <Validity>VALID</Validity>
      </GazePoint>
      <GazePoint>
        <X>502</X>
        <Y>304</Y>
        <TimeTick>438055250681156</TimeTick>
        <Validity>VALID</Validity>
      </GazePoint>
      <GazePoint>
        <X>502</X>
        <Y>304</Y>
        <TimeTick>438055234674255</TimeTick>
        <Validity>VALID</Validity>
      </GazePoint>
      <GazePoint>
        <X>502</X>
        <Y>304</Y>
        <TimeTick>438055218648987</TimeTick>
        <Validity>VALID</Validity>
      </GazePoint>
      <GazePoint>
        <X>502</X>
        <Y>304</Y>
        <TimeTick>438055202619939</TimeTick>
        <Validity>VALID</Validity>
      </GazePoint>
      <GazePoint>
        <X>502</X>
        <Y>304</Y>
        <TimeTick>438055186636806</TimeTick>
        <Validity>VALID</Validity>
      </GazePoint>
      <GazePoint>
        <X>502</X>
        <Y>304</Y>
        <TimeTick>438055170649350</TimeTick>
        <Validity>VALID</Validity>
      </GazePoint>
      <GazePoint>
        <X>502</X>
        <Y>304</Y>
        <TimeTick>438055154029355</TimeTick>
        <Validity>VALID</Validity>
      </GazePoint>
      <GazePoint>
        <X>502</X>
        <Y>304</Y>
        <TimeTick>438055138074310</TimeTick>
        <Validity>VALID</Validity>
      </GazePoint>
      <GazePoint>
        <X>502</X>
        <Y>304</Y>
        <TimeTick>438055121983682</TimeTick>
        <Validity>VALID</Validity>
      </GazePoint>
      <GazePoint>
        <X>502</X>
        <Y>304</Y>
        <TimeTick>438055106023236</TimeTick>
        <Validity>VALID</Validity>
      </GazePoint>
      <GazePoint>
        <X>502</X>
        <Y>304</Y>
        <TimeTick>438055089956915</TimeTick>
        <Validity>VALID</Validity>
      </GazePoint>
      <GazePoint>
        <X>502</X>
        <Y>304</Y>
        <TimeTick>438055073998089</TimeTick>
        <Validity>VALID</Validity>
      </GazePoint>
      <GazePoint>
        <X>502</X>
        <Y>304</Y>
        <TimeTick>438055057925828</TimeTick>
        <Validity>VALID</Validity>
      </GazePoint>
      <GazePoint>
        <X>502</X>
        <Y>304</Y>
        <TimeTick>438055041916225</TimeTick>
        <Validity>VALID</Validity>
      </GazePoint>
      <GazePoint>
        <X>502</X>
        <Y>304</Y>
        <TimeTick>438055025955239</TimeTick>
        <Validity>VALID</Validity>
      </GazePoint>
      <GazePoint>
        <X>502</X>
        <Y>304</Y>
        <TimeTick>438055009947257</TimeTick>
        <Validity>VALID</Validity>
      </GazePoint>
      <GazePoint>
        <X>502</X>
        <Y>304</Y>
        <TimeTick>438054993792889</TimeTick>
        <Validity>VALID</Validity>
      </GazePoint>
      <GazePoint>
        <X>502</X>
        <Y>304</Y>
        <TimeTick>438054977481871</TimeTick>
        <Validity>VALID</Validity>
      </GazePoint>
      <GazePoint>
        <X>502</X>
        <Y>304</Y>
        <TimeTick>438054961446341</TimeTick>
        <Validity>VALID</Validity>
      </GazePoint>
      <GazePoint>
        <X>503</X>
        <Y>304</Y>
        <TimeTick>438054945269286</TimeTick>
        <Validity>VALID</Validity>
      </GazePoint>
      <GazePoint>
        <X>503</X>
        <Y>303</Y>
        <TimeTick>438054929102494</TimeTick>
        <Validity>VALID</Validity>
      </GazePoint>
      <GazePoint>
        <X>503</X>
        <Y>303</Y>
        <TimeTick>438054913441843</TimeTick>
        <Validity>VALID</Validity>
      </GazePoint>
      <GazePoint>
        <X>503</X>
        <Y>301</Y>
        <TimeTick>438054896927180</TimeTick>
        <Validity>VALID</Validity>
      </GazePoint>
      <GazePoint>
        <X>503</X>
        <Y>301</Y>
        <TimeTick>438054880960252</TimeTick>
        <Validity>VALID</Validity>
      </GazePoint>
      <GazePoint>
        <X>503</X>
        <Y>301</Y>
        <TimeTick>438054864769692</TimeTick>
        <Validity>VALID</Validity>
      </GazePoint>
      <GazePoint>
        <X>503</X>
        <Y>301</Y>
        <TimeTick>438054847940650</TimeTick>
        <Validity>VALID</Validity>
      </GazePoint>
      <GazePoint>
        <X>503</X>
        <Y>301</Y>
        <TimeTick>438054831693372</TimeTick>
        <Validity>VALID</Validity>
      </GazePoint>
      <GazePoint>
        <X>503</X>
        <Y>301</Y>
        <TimeTick>438054815705917</TimeTick>
        <Validity>VALID</Validity>
      </GazePoint>
      <GazePoint>
        <X>503</X>
        <Y>301</Y>
        <TimeTick>438054799683891</TimeTick>
        <Validity>VALID</Validity>
      </GazePoint>
      <GazePoint>
        <X>503</X>
        <Y>301</Y>
        <TimeTick>438054784009195</TimeTick>
        <Validity>VALID</Validity>
      </GazePoint>
      <GazePoint>
        <X>503</X>
        <Y>301</Y>
        <TimeTick>438054767684133</TimeTick>
        <Validity>VALID</Validity>
      </GazePoint>
      <GazePoint>
        <X>503</X>
        <Y>301</Y>
        <TimeTick>438054751163529</TimeTick>
        <Validity>VALID</Validity>
      </GazePoint>
      <GazePoint>
        <X>503</X>
        <Y>299</Y>
        <TimeTick>438054735140963</TimeTick>
        <Validity>VALID</Validity>
      </GazePoint>
      <GazePoint>
        <X>503</X>
        <Y>298</Y>
        <TimeTick>438054719173494</TimeTick>
        <Validity>VALID</Validity>
      </GazePoint>
      <GazePoint>
        <X>503</X>
        <Y>298</Y>
        <TimeTick>438054703032090</TimeTick>
        <Validity>VALID</Validity>
      </GazePoint>
      <GazePoint>
        <X>503</X>
        <Y>298</Y>
        <TimeTick>438054686694064</TimeTick>
        <Validity>VALID</Validity>
      </GazePoint>
      <GazePoint>
        <X>503</X>
        <Y>298</Y>
        <TimeTick>438054670628824</TimeTick>
        <Validity>VALID</Validity>
      </GazePoint>
      <GazePoint>
        <X>503</X>
        <Y>298</Y>
        <TimeTick>438054654660275</TimeTick>
        <Validity>VALID</Validity>
      </GazePoint>
      <GazePoint>
        <X>503</X>
        <Y>298</Y>
        <TimeTick>438054638610700</TimeTick>
        <Validity>VALID</Validity>
      </GazePoint>
      <GazePoint>
        <X>503</X>
        <Y>298</Y>
        <TimeTick>438054621807586</TimeTick>
        <Validity>VALID</Validity>
      </GazePoint>
      <GazePoint>
        <X>503</X>
        <Y>298</Y>
        <TimeTick>438054605462538</TimeTick>
        <Validity>VALID</Validity>
      </GazePoint>
      <GazePoint>
        <X>503</X>
        <Y>298</Y>
        <TimeTick>438054589483725</TimeTick>
        <Validity>VALID</Validity>
      </GazePoint>
      <GazePoint>
        <X>503</X>
        <Y>298</Y>
        <TimeTick>438054573199716</TimeTick>
        <Validity>VALID</Validity>
      </GazePoint>
      <GazePoint>
        <X>503</X>
        <Y>298</Y>
        <TimeTick>438054556370674</TimeTick>
        <Validity>VALID</Validity>
      </GazePoint>
      <GazePoint>
        <X>503</X>
        <Y>298</Y>
        <TimeTick>438054540322179</TimeTick>
        <Validity>VALID</Validity>
      </GazePoint>
      <GazePoint>
        <X>503</X>
        <Y>298</Y>
        <TimeTick>438054523328925</TimeTick>
        <Validity>VALID</Validity>
      </GazePoint>
      <GazePoint>
        <X>503</X>
        <Y>298</Y>
        <TimeTick>438054507406831</TimeTick>
        <Validity>VALID</Validity>
      </GazePoint>
      <GazePoint>
        <X>503</X>
        <Y>298</Y>
        <TimeTick>438054491124442</TimeTick>
        <Validity>VALID</Validity>
      </GazePoint>
      <GazePoint>
        <X>503</X>
        <Y>298</Y>
        <TimeTick>438054474691886</TimeTick>
        <Validity>VALID</Validity>
      </GazePoint>
      <GazePoint>
        <X>503</X>
        <Y>298</Y>
        <TimeTick>438054458380328</TimeTick>
        <Validity>VALID</Validity>
      </GazePoint>
      <GazePoint>
        <X>503</X>
        <Y>298</Y>
        <TimeTick>438054441448653</TimeTick>
        <Validity>VALID</Validity>
      </GazePoint>
      <GazePoint>
        <X>503</X>
        <Y>298</Y>
        <TimeTick>438054424492671</TimeTick>
        <Validity>VALID</Validity>
      </GazePoint>
      <GazePoint>
        <X>503</X>
        <Y>298</Y>
        <TimeTick>438054407980169</TimeTick>
        <Validity>VALID</Validity>
      </GazePoint>
      <GazePoint>
        <X>503</X>
        <Y>298</Y>
        <TimeTick>438054391302375</TimeTick>
        <Validity>VALID</Validity>
      </GazePoint>
      <GazePoint>
        <X>503</X>
        <Y>299</Y>
        <TimeTick>438054374943822</TimeTick>
        <Validity>VALID</Validity>
      </GazePoint>
      <GazePoint>
        <X>500</X>
        <Y>299</Y>
        <TimeTick>438054358745700</TimeTick>
        <Validity>VALID</Validity>
      </GazePoint>
      <GazePoint>
        <X>500</X>
        <Y>300</Y>
        <TimeTick>438054342294237</TimeTick>
        <Validity>VALID</Validity>
      </GazePoint>
      <GazePoint>
        <X>498</X>
        <Y>300</Y>
        <TimeTick>438054325360942</TimeTick>
        <Validity>VALID</Validity>
      </GazePoint>
      <GazePoint>
        <X>497</X>
        <Y>302</Y>
        <TimeTick>438054309182266</TimeTick>
        <Validity>VALID</Validity>
      </GazePoint>
      <GazePoint>
        <X>496</X>
        <Y>302</Y>
        <TimeTick>438054293191570</TimeTick>
        <Validity>VALID</Validity>
      </GazePoint>
      <GazePoint>
        <X>496</X>
        <Y>302</Y>
        <TimeTick>438054277180348</TimeTick>
        <Validity>VALID</Validity>
      </GazePoint>
      <GazePoint>
        <X>495</X>
        <Y>302</Y>
        <TimeTick>438054261111327</TimeTick>
        <Validity>VALID</Validity>
      </GazePoint>
      <GazePoint>
        <X>495</X>
        <Y>302</Y>
        <TimeTick>438054244953718</TimeTick>
        <Validity>VALID</Validity>
      </GazePoint>
      <GazePoint>
        <X>495</X>
        <Y>302</Y>
        <TimeTick>438054228864170</TimeTick>
        <Validity>VALID</Validity>
      </GazePoint>
      <GazePoint>
        <X>493</X>
        <Y>304</Y>
        <TimeTick>438054211958424</TimeTick>
        <Validity>VALID</Validity>
      </GazePoint>
      <GazePoint>
        <X>492</X>
        <Y>304</Y>
        <TimeTick>438054195800815</TimeTick>
        <Validity>VALID</Validity>
      </GazePoint>
      <GazePoint>
        <X>491</X>
        <Y>304</Y>
        <TimeTick>438054179803096</TimeTick>
        <Validity>VALID</Validity>
      </GazePoint>
      <GazePoint>
        <X>484</X>
        <Y>310</Y>
        <TimeTick>438054163601733</TimeTick>
        <Validity>VALID</Validity>
      </GazePoint>
      <GazePoint>
        <X>477</X>
        <Y>315</Y>
        <TimeTick>438054147299898</TimeTick>
        <Validity>VALID</Validity>
      </GazePoint>
      <GazePoint>
        <X>472</X>
        <Y>316</Y>
        <TimeTick>438054131325948</TimeTick>
        <Validity>VALID</Validity>
      </GazePoint>
      <GazePoint>
        <X>452</X>
        <Y>320</Y>
        <TimeTick>438054114468816</TimeTick>
        <Validity>VALID</Validity>
      </GazePoint>
      <GazePoint>
        <X>447</X>
        <Y>320</Y>
        <TimeTick>438054098382510</TimeTick>
        <Validity>VALID</Validity>
      </GazePoint>
      <GazePoint>
        <X>441</X>
        <Y>319</Y>
        <TimeTick>438054082612744</TimeTick>
        <Validity>VALID</Validity>
      </GazePoint>
      <GazePoint>
        <X>428</X>
        <Y>315</Y>
        <TimeTick>438054065560611</TimeTick>
        <Validity>VALID</Validity>
      </GazePoint>
      <GazePoint>
        <X>426</X>
        <Y>315</Y>
        <TimeTick>438054049372212</TimeTick>
        <Validity>VALID</Validity>
      </GazePoint>
      <GazePoint>
        <X>421</X>
        <Y>314</Y>
        <TimeTick>438054033402043</TimeTick>
        <Validity>VALID</Validity>
      </GazePoint>
      <GazePoint>
        <X>411</X>
        <Y>310</Y>
        <TimeTick>438054016736132</TimeTick>
        <Validity>VALID</Validity>
      </GazePoint>
      <GazePoint>
        <X>400</X>
        <Y>303</Y>
        <TimeTick>438054000706004</TimeTick>
        <Validity>VALID</Validity>
      </GazePoint>
      <GazePoint>
        <X>393</X>
        <Y>300</Y>
        <TimeTick>438053984783909</TimeTick>
        <Validity>VALID</Validity>
      </GazePoint>
      <GazePoint>
        <X>376</X>
        <Y>295</Y>
        <TimeTick>438053968692741</TimeTick>
        <Validity>VALID</Validity>
      </GazePoint>
      <GazePoint>
        <X>364</X>
        <Y>291</Y>
        <TimeTick>438053952172677</TimeTick>
        <Validity>VALID</Validity>
      </GazePoint>
      <GazePoint>
        <X>352</X>
        <Y>281</Y>
        <TimeTick>438053936204668</TimeTick>
        <Validity>VALID</Validity>
      </GazePoint>
      <GazePoint>
        <X>335</X>
        <Y>270</Y>
        <TimeTick>438053920091894</TimeTick>
        <Validity>VALID</Validity>
      </GazePoint>
      <GazePoint>
        <X>319</X>
        <Y>257</Y>
        <TimeTick>438053904050421</TimeTick>
        <Validity>VALID</Validity>
      </GazePoint>
      <GazePoint>
        <X>312</X>
        <Y>253</Y>
        <TimeTick>438053888079712</TimeTick>
        <Validity>VALID</Validity>
      </GazePoint>
      <GazePoint>
        <X>290</X>
        <Y>236</Y>
        <TimeTick>438053871910219</TimeTick>
        <Validity>VALID</Validity>
      </GazePoint>
      <GazePoint>
        <X>280</X>
        <Y>231</Y>
        <TimeTick>438053855565710</TimeTick>
        <Validity>VALID</Validity>
      </GazePoint>
      <GazePoint>
        <X>270</X>
        <Y>229</Y>
        <TimeTick>438053839685749</TimeTick>
        <Validity>VALID</Validity>
      </GazePoint>
      <GazePoint>
        <X>252</X>
        <Y>225</Y>
        <TimeTick>438053822741651</TimeTick>
        <Validity>VALID</Validity>
      </GazePoint>
      <GazePoint>
        <X>247</X>
        <Y>224</Y>
        <TimeTick>438053806705580</TimeTick>
        <Validity>VALID</Validity>
      </GazePoint>
      <GazePoint>
        <X>244</X>
        <Y>223</Y>
        <TimeTick>438053790886659</TimeTick>
        <Validity>VALID</Validity>
      </GazePoint>
      <GazePoint>
        <X>239</X>
        <Y>223</Y>
        <TimeTick>438053774390362</TimeTick>
        <Validity>VALID</Validity>
      </GazePoint>
      <GazePoint>
        <X>237</X>
        <Y>223</Y>
        <TimeTick>438053757892445</TimeTick>
        <Validity>VALID</Validity>
      </GazePoint>
      <GazePoint>
        <X>237</X>
        <Y>224</Y>
        <TimeTick>438053741576025</TimeTick>
        <Validity>VALID</Validity>
      </GazePoint>
      <GazePoint>
        <X>237</X>
        <Y>224</Y>
        <TimeTick>438053725613958</TimeTick>
        <Validity>VALID</Validity>
      </GazePoint>
      <GazePoint>
        <X>237</X>
        <Y>224</Y>
        <TimeTick>438053708513750</TimeTick>
        <Validity>VALID</Validity>
      </GazePoint>
      <GazePoint>
        <X>237</X>
        <Y>224</Y>
        <TimeTick>438053692139532</TimeTick>
        <Validity>VALID</Validity>
      </GazePoint>
      <GazePoint>
        <X>237</X>
        <Y>224</Y>
        <TimeTick>438053674477546</TimeTick>
        <Validity>VALID</Validity>
      </GazePoint>
      <GazePoint>
        <X>237</X>
        <Y>224</Y>
        <TimeTick>438053657988271</TimeTick>
        <Validity>VALID</Validity>
      </GazePoint>
      <GazePoint>
        <X>237</X>
        <Y>224</Y>
        <TimeTick>438053641587045</TimeTick>
        <Validity>VALID</Validity>
      </GazePoint>
      <GazePoint>
        <X>237</X>
        <Y>224</Y>
        <TimeTick>438053625446181</TimeTick>
        <Validity>VALID</Validity>
      </GazePoint>
      <GazePoint>
        <X>237</X>
        <Y>224</Y>
        <TimeTick>438053609464128</TimeTick>
        <Validity>VALID</Validity>
      </GazePoint>
      <GazePoint>
        <X>237</X>
        <Y>224</Y>
        <TimeTick>438053593475052</TimeTick>
        <Validity>VALID</Validity>
      </GazePoint>
      <GazePoint>
        <X>237</X>
        <Y>224</Y>
        <TimeTick>438053576755665</TimeTick>
        <Validity>VALID</Validity>
      </GazePoint>
      <GazePoint>
        <X>237</X>
        <Y>224</Y>
        <TimeTick>438053560183204</TimeTick>
        <Validity>VALID</Validity>
      </GazePoint>
      <GazePoint>
        <X>237</X>
        <Y>224</Y>
        <TimeTick>438053543681506</TimeTick>
        <Validity>VALID</Validity>
      </GazePoint>
      <GazePoint>
        <X>237</X>
        <Y>224</Y>
        <TimeTick>438053527458536</TimeTick>
        <Validity>VALID</Validity>
      </GazePoint>
      <GazePoint>
        <X>237</X>
        <Y>224</Y>
        <TimeTick>438053511439211</TimeTick>
        <Validity>VALID</Validity>
      </GazePoint>
      <GazePoint>
        <X>237</X>
        <Y>224</Y>
        <TimeTick>438053494518339</TimeTick>
        <Validity>VALID</Validity>
      </GazePoint>
      <GazePoint>
        <X>237</X>
        <Y>224</Y>
        <TimeTick>438053478513059</TimeTick>
        <Validity>VALID</Validity>
      </GazePoint>
      <GazePoint>
        <X>237</X>
        <Y>224</Y>
        <TimeTick>438053462487792</TimeTick>
        <Validity>VALID</Validity>
      </GazePoint>
      <GazePoint>
        <X>237</X>
        <Y>224</Y>
        <TimeTick>438053445595549</TimeTick>
        <Validity>VALID</Validity>
      </GazePoint>
      <GazePoint>
        <X>237</X>
        <Y>224</Y>
        <TimeTick>438053429646446</TimeTick>
        <Validity>VALID</Validity>
      </GazePoint>
      <GazePoint>
        <X>237</X>
        <Y>224</Y>
        <TimeTick>438053413422396</TimeTick>
        <Validity>VALID</Validity>
      </GazePoint>
      <GazePoint>
        <X>237</X>
        <Y>224</Y>
        <TimeTick>438053397208069</TimeTick>
        <Validity>VALID</Validity>
      </GazePoint>
      <GazePoint>
        <X>237</X>
        <Y>224</Y>
        <TimeTick>438053380698268</TimeTick>
        <Validity>VALID</Validity>
      </GazePoint>
      <GazePoint>
        <X>237</X>
        <Y>224</Y>
        <TimeTick>438053364604940</TimeTick>
        <Validity>VALID</Validity>
      </GazePoint>
      <GazePoint>
        <X>237</X>
        <Y>224</Y>
        <TimeTick>438053347536602</TimeTick>
        <Validity>VALID</Validity>
      </GazePoint>
      <GazePoint>
        <X>237</X>
        <Y>224</Y>
        <TimeTick>438053331682569</TimeTick>
        <Validity>VALID</Validity>
      </GazePoint>
      <GazePoint>
        <X>237</X>
        <Y>224</Y>
        <TimeTick>438053315514156</TimeTick>
        <Validity>VALID</Validity>
      </GazePoint>
      <GazePoint>
        <X>237</X>
        <Y>224</Y>
        <TimeTick>438053298669449</TimeTick>
        <Validity>VALID</Validity>
      </GazePoint>
      <GazePoint>
        <X>237</X>
        <Y>224</Y>
        <TimeTick>438053282390302</TimeTick>
        <Validity>VALID</Validity>
      </GazePoint>
      <GazePoint>
        <X>237</X>
        <Y>224</Y>
        <TimeTick>438053266421752</TimeTick>
        <Validity>VALID</Validity>
      </GazePoint>
      <GazePoint>
        <X>237</X>
        <Y>224</Y>
        <TimeTick>438053249539773</TimeTick>
        <Validity>VALID</Validity>
      </GazePoint>
      <GazePoint>
        <X>237</X>
        <Y>224</Y>
        <TimeTick>438053233371901</TimeTick>
        <Validity>VALID</Validity>
      </GazePoint>
      <GazePoint>
        <X>237</X>
        <Y>224</Y>
        <TimeTick>438053216401334</TimeTick>
        <Validity>VALID</Validity>
      </GazePoint>
      <GazePoint>
        <X>237</X>
        <Y>224</Y>
        <TimeTick>438053200311246</TimeTick>
        <Validity>VALID</Validity>
      </GazePoint>
      <GazePoint>
        <X>237</X>
        <Y>224</Y>
        <TimeTick>438053183622649</TimeTick>
        <Validity>VALID</Validity>
      </GazePoint>
      <GazePoint>
        <X>237</X>
        <Y>224</Y>
        <TimeTick>438053167467200</TimeTick>
        <Validity>VALID</Validity>
      </GazePoint>
      <GazePoint>
        <X>237</X>
        <Y>224</Y>
        <TimeTick>438053150604667</TimeTick>
        <Validity>VALID</Validity>
      </GazePoint>
      <GazePoint>
        <X>237</X>
        <Y>224</Y>
        <TimeTick>438053134634498</TimeTick>
        <Validity>VALID</Validity>
      </GazePoint>
      <GazePoint>
        <X>237</X>
        <Y>224</Y>
        <TimeTick>438053118578441</TimeTick>
        <Validity>VALID</Validity>
      </GazePoint>
      <GazePoint>
        <X>237</X>
        <Y>224</Y>
        <TimeTick>438053102461885</TimeTick>
        <Validity>VALID</Validity>
      </GazePoint>
    </RawGazePoints>
    <RawFutureGazePoints>
      <GazePoint>
        <X>502</X>
        <Y>304</Y>
        <TimeTick>438055804103574</TimeTick>
        <Validity>VALID</Validity>
      </GazePoint>
      <GazePoint>
        <X>502</X>
        <Y>304</Y>
        <TimeTick>438055820342209</TimeTick>
        <Validity>VALID</Validity>
      </GazePoint>
      <GazePoint>
        <X>502</X>
        <Y>304</Y>
        <TimeTick>438055836169233</TimeTick>
        <Validity>VALID</Validity>
      </GazePoint>
      <GazePoint>
        <X>502</X>
        <Y>304</Y>
        <TimeTick>438055852112934</TimeTick>
        <Validity>VALID</Validity>
      </GazePoint>
      <GazePoint>
        <X>502</X>
        <Y>304</Y>
        <TimeTick>438055868764800</TimeTick>
        <Validity>VALID</Validity>
      </GazePoint>
      <GazePoint>
        <X>502</X>
        <Y>304</Y>
        <TimeTick>438055884867852</TimeTick>
        <Validity>VALID</Validity>
      </GazePoint>
      <GazePoint>
        <X>502</X>
        <Y>304</Y>
        <TimeTick>438055901055711</TimeTick>
        <Validity>VALID</Validity>
      </GazePoint>
      <GazePoint>
        <X>502</X>
        <Y>304</Y>
        <TimeTick>438055917064773</TimeTick>
        <Validity>VALID</Validity>
      </GazePoint>
      <GazePoint>
        <X>502</X>
        <Y>304</Y>
        <TimeTick>438055933059790</TimeTick>
        <Validity>VALID</Validity>
      </GazePoint>
      <GazePoint>
        <X>502</X>
        <Y>304</Y>
        <TimeTick>438055949083437</TimeTick>
        <Validity>VALID</Validity>
      </GazePoint>
      <GazePoint>
        <X>502</X>
        <Y>304</Y>
        <TimeTick>438055965174064</TimeTick>
        <Validity>VALID</Validity>
      </GazePoint>
      <GazePoint>
        <X>502</X>
        <Y>304</Y>
        <TimeTick>438055981129109</TimeTick>
        <Validity>VALID</Validity>
      </GazePoint>
      <GazePoint>
        <X>502</X>
        <Y>304</Y>
        <TimeTick>438055997130068</TimeTick>
        <Validity>VALID</Validity>
      </GazePoint>
      <GazePoint>
        <X>502</X>
        <Y>304</Y>
        <TimeTick>438056013148313</TimeTick>
        <Validity>VALID</Validity>
      </GazePoint>
      <GazePoint>
        <X>502</X>
        <Y>304</Y>
        <TimeTick>438056029143871</TimeTick>
        <Validity>VALID</Validity>
      </GazePoint>
      <GazePoint>
        <X>502</X>
        <Y>304</Y>
        <TimeTick>438056045174000</TimeTick>
        <Validity>VALID</Validity>
      </GazePoint>
    </RawFutureGazePoints>
  </ResultTarget>
</TestPlanItem>
